mbf_gtf-0.6.0.dist-info/METADATA
mbf_gtf-0.6.0.dist-info/WHEEL
mbf_gtf-0.6.0.dist-info/licenses/LICENSE
mbf_gtf/__init__.py
mbf_gtf/mbf_gtf.abi3.so
mbf_gtf-0.6.0.dist-info/RECORD
