Metadata-Version: 2.4
Name: mbf_gtf
Version: 0.6.0
Classifier: Programming Language :: Rust
Classifier: Programming Language :: Python :: Implementation :: CPython
Classifier: Programming Language :: Python :: Implementation :: PyPy
License-File: LICENSE
Summary: Fast Parser for Ensembl formated GTF Files to Pandas DataFrames
Keywords: gtf
Author: Florian Finkernagel <finkernagel@imt.uni-marburg.de>
Author-email: Florian Finkernagel <finkernagel@imt.uni-marburg.de>
License: MIT
Requires-Python: >=3.7
Project-URL: Source Code, https://github.com/TyberiusPrime/mbf_gtf
